{
  "schema": "ci-taxonomy/v1",
  "repo": "oraclemcp",
  "note": "Generated by scripts/ci_taxonomy.py from trigger-bearing GitHub Actions workflows under .github/workflows/. Do not hand-edit: run scripts/ci_taxonomy.py --write. A required job must be a completed success for a SHA to be releasable; advisory jobs never gate. `workflows` and `groups` are derived views over `jobs`, which is the single source of truth for tiers.",
  "jobs": [
    {
      "check_name": "watch required + scheduled lanes (server + driver)",
      "tier": "scheduled",
      "workflow": "CI Heartbeat",
      "workflow_file": "ci-heartbeat.yml",
      "job_id": "heartbeat",
      "triggers": [
        "schedule",
        "workflow_dispatch"
      ],
      "path_filtered": false
    },
    {
      "check_name": "Oracle FREE 23ai matrix + VECTOR smoke",
      "tier": "required",
      "workflow": "CI",
      "workflow_file": "ci.yml",
      "job_id": "oracle-free23",
      "triggers": [
        "pull_request",
        "push"
      ],
      "path_filtered": false
    },
    {
      "check_name": "PL/SQL intelligence feature matrix",
      "tier": "required",
      "workflow": "CI",
      "workflow_file": "ci.yml",
      "job_id": "plsql-intelligence",
      "triggers": [
        "pull_request",
        "push"
      ],
      "path_filtered": false
    },
    {
      "check_name": "Rust workspace (Windows)",
      "tier": "required",
      "workflow": "CI",
      "workflow_file": "ci.yml",
      "job_id": "windows-rust",
      "triggers": [
        "pull_request",
        "push"
      ],
      "path_filtered": false
    },
    {
      "check_name": "Windows installer PSSA and dry-run",
      "tier": "required",
      "workflow": "CI",
      "workflow_file": "ci.yml",
      "job_id": "windows-installer",
      "triggers": [
        "pull_request",
        "push"
      ],
      "path_filtered": false
    },
    {
      "check_name": "agent ergonomics drift guard",
      "tier": "required",
      "workflow": "CI",
      "workflow_file": "ci.yml",
      "job_id": "ergonomics",
      "triggers": [
        "pull_request",
        "push"
      ],
      "path_filtered": false
    },
    {
      "check_name": "build on pinned nightly",
      "tier": "required",
      "workflow": "CI",
      "workflow_file": "ci.yml",
      "job_id": "pinned-nightly",
      "triggers": [
        "pull_request",
        "push"
      ],
      "path_filtered": false
    },
    {
      "check_name": "build thin driver",
      "tier": "required",
      "workflow": "CI",
      "workflow_file": "ci.yml",
      "job_id": "thin-db",
      "triggers": [
        "pull_request",
        "push"
      ],
      "path_filtered": false
    },
    {
      "check_name": "cargo deny (advisories, licenses, bans, sources)",
      "tier": "required",
      "workflow": "CI",
      "workflow_file": "ci.yml",
      "job_id": "supply-chain",
      "triggers": [
        "pull_request",
        "push"
      ],
      "path_filtered": false
    },
    {
      "check_name": "cargo doc (builds)",
      "tier": "required",
      "workflow": "CI",
      "workflow_file": "ci.yml",
      "job_id": "docs",
      "triggers": [
        "pull_request",
        "push"
      ],
      "path_filtered": false
    },
    {
      "check_name": "cargo test",
      "tier": "required",
      "workflow": "CI",
      "workflow_file": "ci.yml",
      "job_id": "test",
      "triggers": [
        "pull_request",
        "push"
      ],
      "path_filtered": false
    },
    {
      "check_name": "clippy (-D warnings)",
      "tier": "required",
      "workflow": "CI",
      "workflow_file": "ci.yml",
      "job_id": "clippy",
      "triggers": [
        "pull_request",
        "push"
      ],
      "path_filtered": false
    },
    {
      "check_name": "engine-free boundary + surface + driver-seam + honesty + conformance accounting",
      "tier": "required",
      "workflow": "CI",
      "workflow_file": "ci.yml",
      "job_id": "boundary",
      "triggers": [
        "pull_request",
        "push"
      ],
      "path_filtered": false
    },
    {
      "check_name": "feature powerset (cargo hack)",
      "tier": "required",
      "workflow": "CI",
      "workflow_file": "ci.yml",
      "job_id": "feature-powerset",
      "triggers": [
        "pull_request",
        "push"
      ],
      "path_filtered": false
    },
    {
      "check_name": "fuzz targets compile (nightly)",
      "tier": "advisory",
      "workflow": "CI",
      "workflow_file": "ci.yml",
      "job_id": "fuzz-build",
      "triggers": [
        "pull_request",
        "push"
      ],
      "path_filtered": false
    },
    {
      "check_name": "installer lint and built-artifact smoke",
      "tier": "required",
      "workflow": "CI",
      "workflow_file": "ci.yml",
      "job_id": "installer",
      "triggers": [
        "pull_request",
        "push"
      ],
      "path_filtered": false
    },
    {
      "check_name": "multi-nightly early-warning (advisory) (nightly)",
      "tier": "advisory",
      "workflow": "CI",
      "workflow_file": "ci.yml",
      "job_id": "multi-nightly",
      "triggers": [
        "pull_request",
        "push"
      ],
      "path_filtered": false
    },
    {
      "check_name": "public-API lock (cargo public-api + semver-checks)",
      "tier": "required",
      "workflow": "CI",
      "workflow_file": "ci.yml",
      "job_id": "api-lock",
      "triggers": [
        "pull_request",
        "push"
      ],
      "path_filtered": false
    },
    {
      "check_name": "release acceptance suite (B.12)",
      "tier": "required",
      "workflow": "CI",
      "workflow_file": "ci.yml",
      "job_id": "release-acceptance",
      "triggers": [
        "pull_request",
        "push"
      ],
      "path_filtered": false
    },
    {
      "check_name": "release metadata sync",
      "tier": "required",
      "workflow": "CI",
      "workflow_file": "ci.yml",
      "job_id": "release-metadata",
      "triggers": [
        "pull_request",
        "push"
      ],
      "path_filtered": false
    },
    {
      "check_name": "rustfmt",
      "tier": "required",
      "workflow": "CI",
      "workflow_file": "ci.yml",
      "job_id": "fmt",
      "triggers": [
        "pull_request",
        "push"
      ],
      "path_filtered": false
    },
    {
      "check_name": "sensitive-data lint",
      "tier": "required",
      "workflow": "CI",
      "workflow_file": "ci.yml",
      "job_id": "sensitive-data",
      "triggers": [
        "pull_request",
        "push"
      ],
      "path_filtered": false
    },
    {
      "check_name": "web bundle (npm ci + vite build)",
      "tier": "required",
      "workflow": "CI",
      "workflow_file": "ci.yml",
      "job_id": "web-build",
      "triggers": [
        "pull_request",
        "push"
      ],
      "path_filtered": false
    },
    {
      "check_name": "promote attested digest",
      "tier": "manual",
      "workflow": "Docker image provenance repair",
      "workflow_file": "docker.yml",
      "job_id": "promote",
      "triggers": [
        "workflow_dispatch"
      ],
      "path_filtered": false
    },
    {
      "check_name": "verify immutable release source",
      "tier": "manual",
      "workflow": "Docker image provenance repair",
      "workflow_file": "docker.yml",
      "job_id": "verify-release",
      "triggers": [
        "workflow_dispatch"
      ],
      "path_filtered": false
    },
    {
      "check_name": "guard + audit BMC proofs",
      "tier": "required",
      "workflow": "Kani Safety",
      "workflow_file": "kani-safety.yml",
      "job_id": "kani-safety",
      "triggers": [
        "pull_request",
        "push",
        "workflow_dispatch"
      ],
      "path_filtered": false
    },
    {
      "check_name": "guard + audit cargo-mutants",
      "tier": "scheduled",
      "workflow": "Mutation Safety",
      "workflow_file": "mutation-safety.yml",
      "job_id": "mutation-safety",
      "triggers": [
        "schedule",
        "workflow_dispatch"
      ],
      "path_filtered": false
    },
    {
      "check_name": "OCI ADB acceptance",
      "tier": "manual",
      "workflow": "OCI Always Free ADB acceptance",
      "workflow_file": "oci-adb.yml",
      "job_id": "acceptance",
      "triggers": [
        "workflow_dispatch"
      ],
      "path_filtered": false
    },
    {
      "check_name": "publish server.json",
      "tier": "manual",
      "workflow": "Publish to MCP Registry",
      "workflow_file": "publish-mcp.yml",
      "job_id": "publish",
      "triggers": [
        "workflow_dispatch"
      ],
      "path_filtered": false
    },
    {
      "check_name": "validate server.json",
      "tier": "manual",
      "workflow": "Publish to MCP Registry",
      "workflow_file": "publish-mcp.yml",
      "job_id": "validate",
      "triggers": [
        "workflow_dispatch"
      ],
      "path_filtered": false
    },
    {
      "check_name": "verify registry listing",
      "tier": "manual",
      "workflow": "Publish to MCP Registry",
      "workflow_file": "publish-mcp.yml",
      "job_id": "verify",
      "triggers": [
        "workflow_dispatch"
      ],
      "path_filtered": false
    },
    {
      "check_name": "npm/npx release channel is retired",
      "tier": "manual",
      "workflow": "Retired npm wrapper guard",
      "workflow_file": "publish-npm.yml",
      "job_id": "retired",
      "triggers": [
        "workflow_dispatch"
      ],
      "path_filtered": false
    },
    {
      "check_name": "Publish to crates.io",
      "tier": "release",
      "workflow": "Release",
      "workflow_file": "release.yml",
      "job_id": "publish-crates",
      "triggers": [
        "push",
        "workflow_dispatch"
      ],
      "path_filtered": false
    },
    {
      "check_name": "build aarch64-apple-darwin",
      "tier": "release",
      "workflow": "Release",
      "workflow_file": "release.yml",
      "job_id": "build",
      "triggers": [
        "push",
        "workflow_dispatch"
      ],
      "path_filtered": false
    },
    {
      "check_name": "build aarch64-unknown-linux-gnu",
      "tier": "release",
      "workflow": "Release",
      "workflow_file": "release.yml",
      "job_id": "build",
      "triggers": [
        "push",
        "workflow_dispatch"
      ],
      "path_filtered": false
    },
    {
      "check_name": "build aarch64-unknown-linux-musl",
      "tier": "release",
      "workflow": "Release",
      "workflow_file": "release.yml",
      "job_id": "build",
      "triggers": [
        "push",
        "workflow_dispatch"
      ],
      "path_filtered": false
    },
    {
      "check_name": "build on pinned nightly",
      "tier": "release",
      "workflow": "Release",
      "workflow_file": "release.yml",
      "job_id": "pinned-nightly",
      "triggers": [
        "push",
        "workflow_dispatch"
      ],
      "path_filtered": false
    },
    {
      "check_name": "build x86_64-apple-darwin",
      "tier": "release",
      "workflow": "Release",
      "workflow_file": "release.yml",
      "job_id": "build",
      "triggers": [
        "push",
        "workflow_dispatch"
      ],
      "path_filtered": false
    },
    {
      "check_name": "build x86_64-pc-windows-msvc",
      "tier": "release",
      "workflow": "Release",
      "workflow_file": "release.yml",
      "job_id": "build",
      "triggers": [
        "push",
        "workflow_dispatch"
      ],
      "path_filtered": false
    },
    {
      "check_name": "build x86_64-unknown-linux-gnu",
      "tier": "release",
      "workflow": "Release",
      "workflow_file": "release.yml",
      "job_id": "build",
      "triggers": [
        "push",
        "workflow_dispatch"
      ],
      "path_filtered": false
    },
    {
      "check_name": "build x86_64-unknown-linux-musl",
      "tier": "release",
      "workflow": "Release",
      "workflow_file": "release.yml",
      "job_id": "build",
      "triggers": [
        "push",
        "workflow_dispatch"
      ],
      "path_filtered": false
    },
    {
      "check_name": "publish GHCR image",
      "tier": "release",
      "workflow": "Release",
      "workflow_file": "release.yml",
      "job_id": "docker",
      "triggers": [
        "push",
        "workflow_dispatch"
      ],
      "path_filtered": false
    },
    {
      "check_name": "publish GitHub release",
      "tier": "release",
      "workflow": "Release",
      "workflow_file": "release.yml",
      "job_id": "release",
      "triggers": [
        "push",
        "workflow_dispatch"
      ],
      "path_filtered": false
    },
    {
      "check_name": "publish MCP registry entry",
      "tier": "release",
      "workflow": "Release",
      "workflow_file": "release.yml",
      "job_id": "publish-mcp-registry",
      "triggers": [
        "push",
        "workflow_dispatch"
      ],
      "path_filtered": false
    },
    {
      "check_name": "release acceptance suite (B.12)",
      "tier": "release",
      "workflow": "Release",
      "workflow_file": "release.yml",
      "job_id": "release-acceptance",
      "triggers": [
        "push",
        "workflow_dispatch"
      ],
      "path_filtered": false
    },
    {
      "check_name": "release gates",
      "tier": "release",
      "workflow": "Release",
      "workflow_file": "release.yml",
      "job_id": "checks",
      "triggers": [
        "push",
        "workflow_dispatch"
      ],
      "path_filtered": false
    },
    {
      "check_name": "verify MCP registry entry",
      "tier": "release",
      "workflow": "Release",
      "workflow_file": "release.yml",
      "job_id": "verify-mcp-registry",
      "triggers": [
        "push",
        "workflow_dispatch"
      ],
      "path_filtered": false
    },
    {
      "check_name": "web bundle (npm ci + vite build)",
      "tier": "release",
      "workflow": "Release",
      "workflow_file": "release.yml",
      "job_id": "web-build",
      "triggers": [
        "push",
        "workflow_dispatch"
      ],
      "path_filtered": false
    }
  ],
  "workflows": {
    "ci-heartbeat.yml": {
      "name": "CI Heartbeat",
      "triggers": [
        "schedule",
        "workflow_dispatch"
      ],
      "jobs": [
        "watch required + scheduled lanes (server + driver)"
      ]
    },
    "ci.yml": {
      "name": "CI",
      "triggers": [
        "pull_request",
        "push"
      ],
      "jobs": [
        "Oracle FREE 23ai matrix + VECTOR smoke",
        "PL/SQL intelligence feature matrix",
        "Rust workspace (Windows)",
        "Windows installer PSSA and dry-run",
        "agent ergonomics drift guard",
        "build on pinned nightly",
        "build thin driver",
        "cargo deny (advisories, licenses, bans, sources)",
        "cargo doc (builds)",
        "cargo test",
        "clippy (-D warnings)",
        "engine-free boundary + surface + driver-seam + honesty + conformance accounting",
        "feature powerset (cargo hack)",
        "fuzz targets compile (nightly)",
        "installer lint and built-artifact smoke",
        "multi-nightly early-warning (advisory) (nightly)",
        "public-API lock (cargo public-api + semver-checks)",
        "release acceptance suite (B.12)",
        "release metadata sync",
        "rustfmt",
        "sensitive-data lint",
        "web bundle (npm ci + vite build)"
      ]
    },
    "docker.yml": {
      "name": "Docker image provenance repair",
      "triggers": [
        "workflow_dispatch"
      ],
      "jobs": [
        "promote attested digest",
        "verify immutable release source"
      ]
    },
    "kani-safety.yml": {
      "name": "Kani Safety",
      "triggers": [
        "pull_request",
        "push",
        "workflow_dispatch"
      ],
      "jobs": [
        "guard + audit BMC proofs"
      ]
    },
    "mutation-safety.yml": {
      "name": "Mutation Safety",
      "triggers": [
        "schedule",
        "workflow_dispatch"
      ],
      "jobs": [
        "guard + audit cargo-mutants"
      ]
    },
    "oci-adb.yml": {
      "name": "OCI Always Free ADB acceptance",
      "triggers": [
        "workflow_dispatch"
      ],
      "jobs": [
        "OCI ADB acceptance"
      ]
    },
    "publish-mcp.yml": {
      "name": "Publish to MCP Registry",
      "triggers": [
        "workflow_dispatch"
      ],
      "jobs": [
        "publish server.json",
        "validate server.json",
        "verify registry listing"
      ]
    },
    "publish-npm.yml": {
      "name": "Retired npm wrapper guard",
      "triggers": [
        "workflow_dispatch"
      ],
      "jobs": [
        "npm/npx release channel is retired"
      ]
    },
    "release.yml": {
      "name": "Release",
      "triggers": [
        "push",
        "workflow_dispatch"
      ],
      "jobs": [
        "Publish to crates.io",
        "build aarch64-apple-darwin",
        "build aarch64-unknown-linux-gnu",
        "build aarch64-unknown-linux-musl",
        "build on pinned nightly",
        "build x86_64-apple-darwin",
        "build x86_64-pc-windows-msvc",
        "build x86_64-unknown-linux-gnu",
        "build x86_64-unknown-linux-musl",
        "publish GHCR image",
        "publish GitHub release",
        "publish MCP registry entry",
        "release acceptance suite (B.12)",
        "release gates",
        "verify MCP registry entry",
        "web bundle (npm ci + vite build)"
      ]
    }
  },
  "groups": {
    "advisory": [
      "fuzz targets compile (nightly)",
      "multi-nightly early-warning (advisory) (nightly)"
    ],
    "manual": [
      "OCI ADB acceptance",
      "npm/npx release channel is retired",
      "promote attested digest",
      "publish server.json",
      "validate server.json",
      "verify immutable release source",
      "verify registry listing"
    ],
    "release": [
      "Publish to crates.io",
      "build aarch64-apple-darwin",
      "build aarch64-unknown-linux-gnu",
      "build aarch64-unknown-linux-musl",
      "build on pinned nightly",
      "build x86_64-apple-darwin",
      "build x86_64-pc-windows-msvc",
      "build x86_64-unknown-linux-gnu",
      "build x86_64-unknown-linux-musl",
      "publish GHCR image",
      "publish GitHub release",
      "publish MCP registry entry",
      "release acceptance suite (B.12)",
      "release gates",
      "verify MCP registry entry",
      "web bundle (npm ci + vite build)"
    ],
    "required": [
      "Oracle FREE 23ai matrix + VECTOR smoke",
      "PL/SQL intelligence feature matrix",
      "Rust workspace (Windows)",
      "Windows installer PSSA and dry-run",
      "agent ergonomics drift guard",
      "build on pinned nightly",
      "build thin driver",
      "cargo deny (advisories, licenses, bans, sources)",
      "cargo doc (builds)",
      "cargo test",
      "clippy (-D warnings)",
      "engine-free boundary + surface + driver-seam + honesty + conformance accounting",
      "feature powerset (cargo hack)",
      "guard + audit BMC proofs",
      "installer lint and built-artifact smoke",
      "public-API lock (cargo public-api + semver-checks)",
      "release acceptance suite (B.12)",
      "release metadata sync",
      "rustfmt",
      "sensitive-data lint",
      "web bundle (npm ci + vite build)"
    ],
    "scheduled": [
      "guard + audit cargo-mutants",
      "watch required + scheduled lanes (server + driver)"
    ]
  }
}
